yt_supercut/db.py
yt_supercut/main.py
yt_supercut/utils.py
yt_supercut-0.1.8.dist-info/METADATA
yt_supercut-0.1.8.dist-info/WHEEL
yt_supercut-0.1.8.dist-info/entry_points.txt
yt_supercut-0.1.8.dist-info/RECORD
