Metadata-Version: 2.4
Name: yt-supercut
Version: 0.1.8
Summary: 
Author: redraw
Author-email: redraw@sdf.org
Requires-Python: >=3.10,<4.0
Classifier: Programming Language :: Python :: 3
Classifier: Programming Language :: Python :: 3.10
Classifier: Programming Language :: Python :: 3.11
Classifier: Programming Language :: Python :: 3.12
Classifier: Programming Language :: Python :: 3.13
Classifier: Programming Language :: Python :: 3.14
Requires-Dist: appdirs (>=1.4.4,<2.0.0)
Requires-Dist: click (>=8.2.1,<9.0.0)
Requires-Dist: datasette-youtube-embed[datasette] (>=0.1,<0.2)
Requires-Dist: datasette[datasette] (>=0.64.3,<0.65.0)
Requires-Dist: python-frontmatter (>=1.1.0,<2.0.0)
Requires-Dist: sqlite-utils (>=3.32.1,<4.0.0)
Requires-Dist: tabulate (>=0.9.0,<0.10.0)
Requires-Dist: tqdm (>=4.65.0,<5.0.0)
Requires-Dist: typer (>=0.9.4,<0.10.0)
Requires-Dist: webvtt-py (>=0.4.6,<0.5.0)
Requires-Dist: yt-dlp
